Perceptron/__init__.py
Perceptron/perceptron.py
dl_gates_perceptron_pkg-0.0.4.dist-info/LICENSE
dl_gates_perceptron_pkg-0.0.4.dist-info/METADATA
dl_gates_perceptron_pkg-0.0.4.dist-info/WHEEL
dl_gates_perceptron_pkg-0.0.4.dist-info/top_level.txt
dl_gates_perceptron_pkg-0.0.4.dist-info/RECORD
